{"file:///f%3A/DESIGN/Design_Hardware/ToolBoard%20Light%2B/Arduino/Light/src/Light.code-workspace":{"language":"JSON with Comments","code":14,"comment":0,"blank":0},"file:///f%3A/DESIGN/Design_Hardware/ToolBoard%20Light%2B/Arduino/Light/platformio.ini":{"language":"Ini","code":10,"comment":9,"blank":3},"file:///f%3A/DESIGN/Design_Hardware/ToolBoard%20Light%2B/Arduino/Light/src/lit_eeprom.h":{"language":"C++","code":35,"comment":16,"blank":7},"file:///f%3A/DESIGN/Design_Hardware/ToolBoard%20Light%2B/Arduino/Light/src/lit_eeprom.cpp":{"language":"C++","code":280,"comment":217,"blank":48},"file:///f%3A/DESIGN/Design_Hardware/ToolBoard%20Light%2B/Arduino/Light/src/lit_led.cpp":{"language":"C++","code":60,"comment":37,"blank":14},"file:///f%3A/DESIGN/Design_Hardware/ToolBoard%20Light%2B/Arduino/Light/src/main.cpp":{"language":"C++","code":67,"comment":27,"blank":14},"file:///f%3A/DESIGN/Design_Hardware/ToolBoard%20Light%2B/Arduino/Light/src/lit_mqtt.h":{"language":"C++","code":6,"comment":10,"blank":3},"file:///f%3A/DESIGN/Design_Hardware/ToolBoard%20Light%2B/Arduino/Light/src/lit_wifi.h":{"language":"C++","code":7,"comment":13,"blank":3},"file:///f%3A/DESIGN/Design_Hardware/ToolBoard%20Light%2B/Arduino/Light/src/lit_led.h":{"language":"C++","code":6,"comment":10,"blank":3},"file:///f%3A/DESIGN/Design_Hardware/ToolBoard%20Light%2B/Arduino/Light/src/lit_wifi.cpp":{"language":"C++","code":99,"comment":46,"blank":17},"file:///f%3A/DESIGN/Design_Hardware/ToolBoard%20Light%2B/Arduino/Light/src/lit_mqtt.cpp":{"language":"C++","code":113,"comment":47,"blank":24}}